yt_dlp_plugins/extractor/brighteon.py
ytdlp_brighteon-2024.4.26.dist-info/licenses/LICENSE
ytdlp_brighteon-2024.4.26.dist-info/METADATA
ytdlp_brighteon-2024.4.26.dist-info/WHEEL
ytdlp_brighteon-2024.4.26.dist-info/top_level.txt
ytdlp_brighteon-2024.4.26.dist-info/RECORD
